s3tar/__init__.py
s3tar/star.py
s3tar-1.4.1.dist-info/entry_points.txt
s3tar-1.4.1.dist-info/WHEEL
s3tar-1.4.1.dist-info/METADATA
s3tar-1.4.1.dist-info/RECORD
