Metadata-Version: 2.1
Name: s3tar
Version: 1.4.1
Summary: Pulls (filtered) files from S3 and adds them to a tar archive.
Home-page: https://github.com/ccdale/s3tar
License: GPL-3.0-or-later
Author: Chris Allison
Author-email: chris.charles.allison+s3tar@gmail.com
Requires-Python: >=3.6,<4.0
Classifier: License :: OSI Approved :: GNU General Public License v3 or later (GPLv3+)
Classifier: Programming Language :: Python :: 3
Classifier: Programming Language :: Python :: 3.6
Classifier: Programming Language :: Python :: 3.7
Classifier: Programming Language :: Python :: 3.8
Requires-Dist: ccaaws (>=0.4.6,<0.5.0)
Requires-Dist: click (>=7.1.1,<8.0.0)
Project-URL: Repository, https://github.com/ccdale/s3tar
